LICENSE
MANIFEST.in
README.md
define.1
setup.py
define/__init__.py
define/__version__.py
define/define.py
define.egg-info/PKG-INFO
define.egg-info/SOURCES.txt
define.egg-info/dependency_links.txt
define.egg-info/entry_points.txt
define.egg-info/requires.txt
define.egg-info/top_level.txt