Metadata-Version: 1.1
Name: define
Version: 1.73
Summary: Terminal Dictionary
Home-page: https://github.com/SethDusek/define
Author: SethDusek
Author-email: shibe@openmailbox.org
License: BSD
Platform: UNKNOWN
Classifier: Intended Audience :: End Users/Desktop
Classifier: Programming Language :: Python :: 2
Classifier: Programming Language :: Python :: 3
